MANIFEST.in
README.md
setup.py
sqlchain-api
sqlchain-config
sqlchain-electrum
sqlchaind
docs/ALTCOINS.md
docs/ENGINES.md
docs/INSTALL.md
etc/dbinfo.sql
etc/deploy
etc/dogecoin.sql
etc/electrum.banner
etc/nginx.template
etc/node.log.template
etc/post-receive
etc/reddcoin.sql
etc/sqlchain.log.template
etc/sqlchain.sql
etc/systemd.template
sqlchain/__init__.py
sqlchain/bci.py
sqlchain/blkdat.py
sqlchain/dbpool.py
sqlchain/democvt.py
sqlchain/insight.py
sqlchain/rpc.py
sqlchain/util.py
sqlchain/version.py
sqlchain.egg-info/PKG-INFO
sqlchain.egg-info/SOURCES.txt
sqlchain.egg-info/dependency_links.txt
sqlchain.egg-info/pbr.json
sqlchain.egg-info/requires.txt
sqlchain.egg-info/top_level.txt
www/404.html
www/main.html
www/wstest.html
www/css/bootstrap.css
www/css/bootstrap.min.css
www/css/main.css
www/css/signin.css
www/fonts/glyphicons-halflings-regular.eot
www/fonts/glyphicons-halflings-regular.svg
www/fonts/glyphicons-halflings-regular.ttf
www/fonts/glyphicons-halflings-regular.woff
www/fonts/glyphicons-halflings-regular.woff2
www/img/favicon.png
www/img/glyphicons-halflings-white.png
www/img/glyphicons-halflings.png
www/img/loading.gif
www/js/bootstrap.js
www/js/bootstrap.min.js
www/js/ie10-viewport-bug-workaround.js
www/js/jquery.min.js
www/js/main.js