Metadata-Version: 1.1
Name: sqlchain
Version: 0.2.6
Summary: Compact SQL layer for Bitcoin blockchain.
Home-page: https://github.com/neocogent/sqlchain
Author: neoCogent.com
Author-email: info@neocogent.com
License: MIT
Download-URL: https://github.com/neocogent/sqlchain/tarball/0.2.6
Keywords: bitcoin sql blockchain api websocket rpc server
Platform: UNKNOWN
Classifier: Development Status :: 4 - Beta
Classifier: Intended Audience :: Developers
Classifier: Intended Audience :: System Administrators
Classifier: Operating System :: POSIX :: Linux
Classifier: Topic :: Database :: Database Engines/Servers
Classifier: Topic :: Internet :: WWW/HTTP :: WSGI :: Server
Classifier: Topic :: Office/Business :: Financial
Classifier: License :: OSI Approved :: MIT License
Classifier: Programming Language :: Python :: 2.7
